cloudshell/__init__.py
cloudshell/networking/__init__.py
cloudshell/networking/arista/__init__.py
cloudshell/networking/arista/cli/__init__.py
cloudshell/networking/arista/cli/arista_cli_configurator.py
cloudshell/networking/arista/cli/arista_command_modes.py
cloudshell/networking/arista/cli/sessions/__init__.py
cloudshell/networking/arista/cli/sessions/console_ssh_session.py
cloudshell/networking/arista/cli/sessions/console_telnet_session.py
cloudshell/networking/arista/command_actions/__init__.py
cloudshell/networking/arista/command_actions/add_remove_vlan_actions.py
cloudshell/networking/arista/command_actions/enable_disable_snmp_actions.py
cloudshell/networking/arista/command_actions/iface_actions.py
cloudshell/networking/arista/command_actions/system_actions.py
cloudshell/networking/arista/command_templates/__init__.py
cloudshell/networking/arista/command_templates/add_remove_vlan.py
cloudshell/networking/arista/command_templates/arista_configuration_templates.py
cloudshell/networking/arista/command_templates/configuration.py
cloudshell/networking/arista/command_templates/firmware.py
cloudshell/networking/arista/command_templates/iface.py
cloudshell/networking/arista/flows/__init__.py
cloudshell/networking/arista/flows/arista_autoload_flow.py
cloudshell/networking/arista/flows/arista_configuration_flow.py
cloudshell/networking/arista/flows/arista_connectivity_flow.py
cloudshell/networking/arista/flows/arista_load_firmware_flow.py
cloudshell/networking/arista/flows/enable_disable_snmp.py
cloudshell/networking/arista/snmp/__init__.py
cloudshell/networking/arista/snmp/mibs/ARISTA-PRODUCTS-MIB.py
cloudshell/networking/arista/snmp/mibs/ARISTA-SMI-MIB.py
cloudshell/networking/arista/snmp/mibs/__init__.py
tests/__init__.py
tests/networking/__init__.py
tests/networking/arista/__init__.py
tests/networking/arista/base_test.py
tests/networking/arista/cli/__init__.py
tests/networking/arista/cli/tests_arista_cli_configurator.py
cloudshell_networking_arista-3.0.4.dist-info/LICENSE.htm
cloudshell_networking_arista-3.0.4.dist-info/METADATA
cloudshell_networking_arista-3.0.4.dist-info/WHEEL
cloudshell_networking_arista-3.0.4.dist-info/top_level.txt
cloudshell_networking_arista-3.0.4.dist-info/RECORD
