Metadata-Version: 2.1
Name: cloudshell-networking-arista
Version: 3.0.4
Summary: QualiSystems Python package
Home-page: https://github.com/QualiSystems/cloudshell-networking-arista
Author: QualiSystems
Author-email: info@qualisystems.com
Requires-Python: ~=3.7
License-File: LICENSE.htm
Requires-Dist: cloudshell-snmp (~=4.0)
Requires-Dist: cloudshell-snmp-autoload (~=1.0)
Requires-Dist: cloudshell-cli (~=4.0)
Requires-Dist: cloudshell-shell-connectivity-flow (~=3.0)
Requires-Dist: cloudshell-shell-flows (~=2.0)
Requires-Dist: attrs (~=21.0)
